netcheckup/__init__.py
netcheckup/__main__.py
netcheckup/core.py
netcheckup-0.2.0.dist-info/licenses/LICENSE
netcheckup-0.2.0.dist-info/licenses/LICENSE.txt
netcheckup-0.2.0.dist-info/METADATA
netcheckup-0.2.0.dist-info/WHEEL
netcheckup-0.2.0.dist-info/entry_points.txt
netcheckup-0.2.0.dist-info/top_level.txt
netcheckup-0.2.0.dist-info/RECORD
