Metadata-Version: 2.4
Name: netcheckup
Version: 0.2.0
Summary: A simple internet health diagnostic tool
Author: akhilsudhakaran
License: MIT
Project-URL: Homepage, https://github.com/AkhilSu/netcheckup
Project-URL: Repository, https://github.com/AkhilSu/netcheckup
Requires-Python: >=3.7
License-File: LICENSE
License-File: LICENSE.txt
Requires-Dist: speedtest-cli
Dynamic: license-file
